{
"Datasets": [{"Dataset": {"name":"2011 - 2013 Indiana Statewide Lidar",
"identifier":{ 
"@type": "PropertyValue",
"propertyID": "opentopoID",
"value": "OTLAS.062012.4326.1"
}, 
"alternateName":"IN_2011_2013",
"url": "https:\/\/doi.org\/10.5069\/G9959FHZ",
"fileFormat": "Point Cloud Data",
"dateCreated": "2012-10-30",
"temporalCoverage": "2011-03-13 \/ 2012-04-30",
"spatialCoverage": {
"@type": "Place",
"additionalProperty": [{
"@type": "PropertyValue",
"additionalType": "CoordinatesSystem",
"name": "Horizontal Coordinates",
"value": "WGS84"
}, {
"@type": "PropertyValue",
"additionalType": "CoordinatesSystem",
"name": "Vertical Coordinates",
"value": "NAVD88"
}, {
"@type": "PropertyValue",
"additionalType": "CoordinatesSystem",
"name": "EPSG (Horizontal)",
"value": "4326"
}],
"variableMeasured": [{
"@type": "PropertyValue",
"name": "Area",
"value": "96094.7 km2"
}, {
"@type": "PropertyValue",
"name": "Unit",
"value": "degree"
}]
}
}
}
,{"Dataset": {"name":"IN Statewide Opt2 B3 2017",
"identifier":{ 
"@type": "PropertyValue",
"propertyID": "USGS_3DEP_ID",
"value": "IN_Statewide_Opt2_B3_2017"
}, 
"fileFormat": "Point Cloud Data",
"dateCreated": "2021-01-13",
"temporalCoverage": "2017-03-28 \/ 2019-06-30",
"spatialCoverage": {
"@type": "Place",
"additionalProperty": [{
"@type": "PropertyValue",
"additionalType": "CoordinatesSystem",
"name": "Horizontal Coordinates",
"value": "WGS84 Web Mercator"
}, {
"@type": "PropertyValue",
"additionalType": "CoordinatesSystem",
"name": "Vertical Coordinates",
"value": "NAVD88 height - Geoid12B (ftUS)"
}, {
"@type": "PropertyValue",
"additionalType": "CoordinatesSystem",
"name": "EPSG (Horizontal)",
"value": "3857"
}],
"variableMeasured": [{
"@type": "PropertyValue",
"name": "Area",
"value": "8073.7 km2"
}, {
"@type": "PropertyValue",
"name": "Unit",
"value": "meter"
}]
}
}
}
,{"Dataset": {"name":"USGS LPC IN WT B11 Putnam 2013 LAS 2016",
"identifier":{ 
"@type": "PropertyValue",
"propertyID": "USGS_3DEP_ID",
"value": "USGS_LPC_IN_WT_B11_Putnam_2013_LAS_2016"
}, 
"fileFormat": "Point Cloud Data",
"dateCreated": "2016-06-14",
"temporalCoverage": "2013-02-14 \/ 2013-04-14",
"spatialCoverage": {
"@type": "Place",
"additionalProperty": [{
"@type": "PropertyValue",
"additionalType": "CoordinatesSystem",
"name": "Horizontal Coordinates",
"value": "WGS84 Web Mercator"
}, {
"@type": "PropertyValue",
"additionalType": "CoordinatesSystem",
"name": "Vertical Coordinates",
"value": "NAVD88 - Geoid09 (Feet)"
}, {
"@type": "PropertyValue",
"additionalType": "CoordinatesSystem",
"name": "EPSG (Horizontal)",
"value": "3857"
}],
"variableMeasured": [{
"@type": "PropertyValue",
"name": "Area",
"value": "1424.32 km2"
}, {
"@type": "PropertyValue",
"name": "Unit",
"value": "meter"
}]
}
}
}
]
}
